requests_ratelimit_adapter/__init__.py
requests_ratelimit_adapter/requests_ratelimit_adapter.py
requests_ratelimit_adapter-0.2.0.dist-info/AUTHORS.rst
requests_ratelimit_adapter-0.2.0.dist-info/LICENSE
requests_ratelimit_adapter-0.2.0.dist-info/METADATA
requests_ratelimit_adapter-0.2.0.dist-info/WHEEL
requests_ratelimit_adapter-0.2.0.dist-info/top_level.txt
requests_ratelimit_adapter-0.2.0.dist-info/RECORD
