Metadata-Version: 2.1
Name: requests-ratelimit-adapter
Version: 0.2.0
Summary: A ratelimiting Session adapter for requests.
Home-page: https://github.com/cmeister2/requests_ratelimit_adapter
Author: Max Dymond
Author-email: cmeister2@gmail.com
License: MIT license
Keywords: requests_ratelimit_adapter
Platform: UNKNOWN
Classifier: Development Status :: 2 - Pre-Alpha
Classifier: Intended Audience :: Developers
Classifier: License :: OSI Approved :: MIT License
Classifier: Natural Language :: English
Classifier: Programming Language :: Python :: 2
Classifier: Programming Language :: Python :: 2.7
Classifier: Programming Language :: Python :: 3
Classifier: Programming Language :: Python :: 3.4
Classifier: Programming Language :: Python :: 3.5
Classifier: Programming Language :: Python :: 3.6
Classifier: Programming Language :: Python :: 3.7
Requires-Dist: requests
